finnr-2025.9.5.0.dist-info/METADATA
finnr-2025.9.5.0.dist-info/WHEEL
finnr-2025.9.5.0.dist-info/entry_points.txt
finnr/__init__.py
finnr/_moneymath.py
finnr/_types.py
finnr/currency.py
finnr/exceptions.py
finnr/iso.py
finnr/money.py
finnr/py.typed
finnr-2025.9.5.0.dist-info/RECORD
