Metadata-Version: 2.1
Name: finnr
Version: 2025.9.5.0
Summary: A high-quality, typed package for financial datatypes in python
Requires-Python: >=3.12
Requires-Dist: docnote>=2025.8.5.0
